main.py
wayspiritmcp_base-0.1.0.dist-info/METADATA
wayspiritmcp_base-0.1.0.dist-info/WHEEL
wayspiritmcp_base-0.1.0.dist-info/entry_points.txt
wayspiritmcp_base-0.1.0.dist-info/top_level.txt
wayspiritmcp_base-0.1.0.dist-info/RECORD
