Metadata-Version: 2.4
Name: wayspiritmcp-base
Version: 0.1.0
Summary: weather server for baseline
Requires-Python: >=3.13
Requires-Dist: httpx>=0.28.1
Requires-Dist: mcp>=1.20.0
